{
  "file_path": "src/modules/order/order.schema.ts",
  "main_branch_history": [],
  "task_views": {
    "001-create": {
      "task_id": "001-create",
      "branch_point": {
        "commit_hash": "e2c14236dedadbadc7b19d123890e3f98e7316c0",
        "content": "",
        "timestamp": "2026-02-01T08:03:23.990755"
      },
      "worktree_state": {
        "content": "/**\n * Order Module Zod Schemas\n *\n * Validation schemas for all Order module inputs/outputs.\n * Follows the validation rules defined in CODING_STANDARDS.md.\n *\n * @module modules/order/schema\n *\n * @example\n * ```typescript\n * import {\n *   createOrderSchema,\n *   createTableSchema,\n *   changeOrderStatusSchema,\n * } from '@/modules/order/order.schema';\n *\n * // Validate order input\n * const validatedData = createOrderSchema.parse(req.body);\n * ```\n */\n\nimport { z } from 'zod';\n\n// -----------------------------------------------------------------------------\n// Constants\n// -----------------------------------------------------------------------------\n\n/**\n * Default limits for order module\n */\nconst LIMITS = {\n  name: { min: 1, max: 100 },\n  tableNumber: { min: 1, max: 20 },\n  notes: { max: 500 },\n  message: { max: 500 },\n  comment: { max: 2000 },\n  reason: { max: 500 },\n  quantity: { min: 1, max: 999 },\n  capacity: { min: 1, max: 50 },\n  sortOrder: { min: 0, max: 10000 },\n  rating: { min: 1, max: 5 },\n  price: { min: 0, max: 999999.99 },\n  taxRate: { min: 0, max: 100 },\n  maxItemsPerOrder: { min: 1, max: 100 },\n} as const;\n\n/**\n * Color validation regex (hex color)\n */\nconst HEX_COLOR_REGEX = /^#([A-Fa-f0-9]{6}|[A-Fa-f0-9]{3})$/;\n\n// -----------------------------------------------------------------------------\n// Enum Schemas\n// -----------------------------------------------------------------------------\n\n/**\n * Order status enum schema\n */\nexport const orderStatusSchema = z.enum([\n  'PENDING',\n  'CONFIRMED',\n  'PREPARING',\n  'READY',\n  'DELIVERED',\n  'COMPLETED',\n  'CANCELLED',\n]);\n\n/**\n * Order type enum schema\n */\nexport const orderTypeSchema = z.enum(['DINE_IN', 'TAKEAWAY', 'DELIVERY']);\n\n/**\n * Order item status enum schema\n */\nexport const orderItemStatusSchema = z.enum(['PENDING', 'PREPARING', 'READY', 'SERVED']);\n\n/**\n * Table status enum schema\n */\nexport const tableStatusSchema = z.enum(['AVAILABLE', 'OCCUPIED', 'RESERVED']);\n\n/**\n * QR code type enum schema\n */\nexport const qrCodeTypeSchema = z.enum(['MENU', 'TABLE', 'CAMPAIGN']);\n\n/**\n * Service request type enum schema\n */\nexport const serviceRequestTypeSchema = z.enum(['CALL_WAITER', 'REQUEST_BILL', 'CUSTOM']);\n\n// -----------------------------------------------------------------------------\n// Base Schemas\n// -----------------------------------------------------------------------------\n\n/**\n * CUID schema\n */\nexport const cuidSchema = z.string().cuid('Invalid ID format');\n\n/**\n * Optional CUID schema\n */\nexport const optionalCuidSchema = z.string().cuid('Invalid ID format').optional().nullable();\n\n/**\n * Name schema\n */\nexport const nameSchema = z\n  .string()\n  .trim()\n  .min(LIMITS.name.min, 'Name is required')\n  .max(LIMITS.name.max, `Name must be at most ${LIMITS.name.max} characters`);\n\n/**\n * Table number schema\n */\nexport const tableNumberSchema = z\n  .string()\n  .trim()\n  .min(LIMITS.tableNumber.min, 'Table number is required')\n  .max(LIMITS.tableNumber.max, `Table number must be at most ${LIMITS.tableNumber.max} characters`);\n\n/**\n * Notes schema (order/item notes)\n */\nexport const notesSchema = z\n  .string()\n  .trim()\n  .max(LIMITS.notes.max, `Notes must be at most ${LIMITS.notes.max} characters`)\n  .optional()\n  .nullable();\n\n/**\n * Comment schema (feedback)\n */\nexport const commentSchema = z\n  .string()\n  .trim()\n  .max(LIMITS.comment.max, `Comment must be at most ${LIMITS.comment.max} characters`)\n  .optional()\n  .nullable();\n\n/**\n * Message schema (service request)\n */\nexport const messageSchema = z\n  .string()\n  .trim()\n  .max(LIMITS.message.max, `Message must be at most ${LIMITS.message.max} characters`)\n  .optional();\n\n/**\n * Cancel reason schema\n */\nexport const cancelReasonSchema = z\n  .string()\n  .trim()\n  .max(LIMITS.reason.max, `Reason must be at most ${LIMITS.reason.max} characters`)\n  .optional();\n\n/**\n * Quantity schema\n */\nexport const quantitySchema = z\n  .number()\n  .int()\n  .min(LIMITS.quantity.min, `Quantity must be at least ${LIMITS.quantity.min}`)\n  .max(LIMITS.quantity.max, `Quantity must be at most ${LIMITS.quantity.max}`);\n\n/**\n * Optional quantity schema\n */\nexport const optionalQuantitySchema = quantitySchema.optional();\n\n/**\n * Capacity schema\n */\nexport const capacitySchema = z\n  .number()\n  .int()\n  .min(LIMITS.capacity.min, `Capacity must be at least ${LIMITS.capacity.min}`)\n  .max(LIMITS.capacity.max, `Capacity must be at most ${LIMITS.capacity.max}`);\n\n/**\n * Sort order schema\n */\nexport const sortOrderSchema = z\n  .number()\n  .int()\n  .min(LIMITS.sortOrder.min)\n  .max(LIMITS.sortOrder.max)\n  .optional()\n  .default(0);\n\n/**\n * Rating schema (1-5)\n */\nexport const ratingSchema = z\n  .number()\n  .int()\n  .min(LIMITS.rating.min, `Rating must be at least ${LIMITS.rating.min}`)\n  .max(LIMITS.rating.max, `Rating must be at most ${LIMITS.rating.max}`);\n\n/**\n * Price schema\n */\nexport const priceSchema = z\n  .union([z.string(), z.number()])\n  .transform((val) => (typeof val === 'string' ? parseFloat(val) : val))\n  .refine((val) => !isNaN(val), 'Price must be a valid number')\n  .refine((val) => val >= LIMITS.price.min, `Price must be at least ${LIMITS.price.min}`)\n  .refine((val) => val <= LIMITS.price.max, `Price must be at most ${LIMITS.price.max}`);\n\n/**\n * Hex color schema\n */\nexport const hexColorSchema = z\n  .string()\n  .regex(HEX_COLOR_REGEX, 'Invalid hex color format (e.g., #FF5733)')\n  .optional()\n  .nullable();\n\n/**\n * Date schema (accepts string or Date)\n */\nexport const dateSchema = z.coerce.date().optional();\n\n// -----------------------------------------------------------------------------\n// Zone Schemas\n// -----------------------------------------------------------------------------\n\n/**\n * Create zone schema\n */\nexport const createZoneSchema = z.object({\n  name: nameSchema,\n  color: hexColorSchema,\n  sortOrder: sortOrderSchema,\n});\n\nexport type CreateZoneInput = z.infer<typeof createZoneSchema>;\n\n/**\n * Update zone schema\n */\nexport const updateZoneSchema = z.object({\n  name: nameSchema.optional(),\n  color: hexColorSchema,\n  sortOrder: sortOrderSchema.optional(),\n});\n\nexport type UpdateZoneInput = z.infer<typeof updateZoneSchema>;\n\n/**\n * List zones query schema\n */\nexport const listZonesQuerySchema = z.object({\n  search: z.string().trim().max(100).optional(),\n  page: z.coerce.number().int().positive().optional().default(1),\n  perPage: z.coerce.number().int().positive().max(100).optional().default(50),\n});\n\nexport type ListZonesQueryInput = z.infer<typeof listZonesQuerySchema>;\n\n// -----------------------------------------------------------------------------\n// Table Schemas\n// -----------------------------------------------------------------------------\n\n/**\n * Create table schema\n */\nexport const createTableSchema = z.object({\n  number: tableNumberSchema,\n  capacity: capacitySchema,\n  branchId: optionalCuidSchema,\n  zoneId: optionalCuidSchema,\n  status: tableStatusSchema.optional().default('AVAILABLE'),\n  sortOrder: sortOrderSchema,\n});\n\nexport type CreateTableInput = z.infer<typeof createTableSchema>;\n\n/**\n * Update table schema\n */\nexport const updateTableSchema = z.object({\n  number: tableNumberSchema.optional(),\n  capacity: capacitySchema.optional(),\n  branchId: optionalCuidSchema,\n  zoneId: optionalCuidSchema,\n  status: tableStatusSchema.optional(),\n  sortOrder: sortOrderSchema.optional(),\n});\n\nexport type UpdateTableInput = z.infer<typeof updateTableSchema>;\n\n/**\n * Change table status schema\n */\nexport const changeTableStatusSchema = z.object({\n  status: tableStatusSchema,\n});\n\nexport type ChangeTableStatusInput = z.infer<typeof changeTableStatusSchema>;\n\n/**\n * List tables query schema\n */\nexport const listTablesQuerySchema = z.object({\n  branchId: optionalCuidSchema,\n  zoneId: optionalCuidSchema,\n  status: tableStatusSchema.optional(),\n  search: z.string().trim().max(100).optional(),\n  page: z.coerce.number().int().positive().optional().default(1),\n  perPage: z.coerce.number().int().positive().max(100).optional().default(50),\n  sortBy: z.enum(['number', 'capacity', 'sortOrder', 'createdAt']).optional().default('sortOrder'),\n  sortOrder: z.enum(['asc', 'desc']).optional().default('asc'),\n});\n\nexport type ListTablesQueryInput = z.infer<typeof listTablesQuerySchema>;\n\n// -----------------------------------------------------------------------------\n// QR Code Schemas\n// -----------------------------------------------------------------------------\n\n/**\n * Create QR code schema\n */\nexport const createQRCodeSchema = z.object({\n  menuId: cuidSchema,\n  tableId: optionalCuidSchema,\n  type: qrCodeTypeSchema.optional().default('MENU'),\n  expiresAt: dateSchema,\n});\n\nexport type CreateQRCodeInput = z.infer<typeof createQRCodeSchema>;\n\n/**\n * Update QR code schema\n */\nexport const updateQRCodeSchema = z.object({\n  isActive: z.boolean().optional(),\n  expiresAt: dateSchema.nullable(),\n});\n\nexport type UpdateQRCodeInput = z.infer<typeof updateQRCodeSchema>;\n\n/**\n * List QR codes query schema\n */\nexport const listQRCodesQuerySchema = z.object({\n  menuId: optionalCuidSchema,\n  tableId: optionalCuidSchema,\n  type: qrCodeTypeSchema.optional(),\n  isActive: z\n    .string()\n    .transform((val) => val === 'true')\n    .optional(),\n  page: z.coerce.number().int().positive().optional().default(1),\n  perPage: z.coerce.number().int().positive().max(100).optional().default(50),\n});\n\nexport type ListQRCodesQueryInput = z.infer<typeof listQRCodesQuerySchema>;\n\n// -----------------------------------------------------------------------------\n// Order Schemas\n// -----------------------------------------------------------------------------\n\n/**\n * Order item modifier schema\n */\nexport const orderItemModifierSchema = z.object({\n  id: cuidSchema,\n  quantity: z.number().int().min(1).max(10).optional().default(1),\n});\n\n/**\n * Create order item schema (nested)\n */\nexport const createOrderItemSchema = z.object({\n  productId: cuidSchema,\n  variantId: optionalCuidSchema,\n  quantity: quantitySchema,\n  notes: notesSchema,\n  modifiers: z.array(orderItemModifierSchema).optional().default([]),\n});\n\nexport type CreateOrderItemInput = z.infer<typeof createOrderItemSchema>;\n\n/**\n * Create order schema\n */\nexport const createOrderSchema = z.object({\n  tableId: optionalCuidSchema,\n  customerId: optionalCuidSchema,\n  type: orderTypeSchema.optional().default('DINE_IN'),\n  notes: notesSchema,\n  items: z.array(createOrderItemSchema).min(1, 'At least one item is required'),\n});\n\nexport type CreateOrderInput = z.infer<typeof createOrderSchema>;\n\n/**\n * Update order schema\n */\nexport const updateOrderSchema = z.object({\n  notes: notesSchema,\n  staffId: optionalCuidSchema,\n});\n\nexport type UpdateOrderInput = z.infer<typeof updateOrderSchema>;\n\n/**\n * Change order status schema\n */\nexport const changeOrderStatusSchema = z.object({\n  status: orderStatusSchema,\n  reason: cancelReasonSchema,\n});\n\nexport type ChangeOrderStatusInput = z.infer<typeof changeOrderStatusSchema>;\n\n/**\n * Add order item schema\n */\nexport const addOrderItemSchema = createOrderItemSchema;\n\nexport type AddOrderItemInput = z.infer<typeof addOrderItemSchema>;\n\n/**\n * Update order item schema\n */\nexport const updateOrderItemSchema = z.object({\n  quantity: optionalQuantitySchema,\n  notes: notesSchema,\n  status: orderItemStatusSchema.optional(),\n});\n\nexport type UpdateOrderItemInput = z.infer<typeof updateOrderItemSchema>;\n\n/**\n * List orders query schema\n */\nexport const listOrdersQuerySchema = z.object({\n  status: orderStatusSchema.optional(),\n  type: orderTypeSchema.optional(),\n  branchId: optionalCuidSchema,\n  tableId: optionalCuidSchema,\n  customerId: optionalCuidSchema,\n  dateFrom: dateSchema,\n  dateTo: dateSchema,\n  search: z.string().trim().max(100).optional(),\n  include: z\n    .string()\n    .transform((val) => val.split(',') as Array<'items' | 'table' | 'customer' | 'feedback'>)\n    .optional(),\n  page: z.coerce.number().int().positive().optional().default(1),\n  perPage: z.coerce.number().int().positive().max(100).optional().default(20),\n  sortBy: z.enum(['orderNumber', 'totalAmount', 'createdAt', 'status']).optional().default('createdAt'),\n  sortOrder: z.enum(['asc', 'desc']).optional().default('desc'),\n});\n\nexport type ListOrdersQueryInput = z.infer<typeof listOrdersQuerySchema>;\n\n// -----------------------------------------------------------------------------\n// Customer Schemas\n// -----------------------------------------------------------------------------\n\n/**\n * Create customer schema\n */\nexport const createCustomerSchema = z\n  .object({\n    email: z.string().email('Invalid email format').optional(),\n    phone: z\n      .string()\n      .regex(/^\\+?[0-9]{10,15}$/, 'Invalid phone number format')\n      .optional(),\n    firstName: z.string().trim().max(100).optional(),\n    lastName: z.string().trim().max(100).optional(),\n    notes: notesSchema,\n    metadata: z.record(z.unknown()).optional().default({}),\n  })\n  .refine((data) => data.email || data.phone, {\n    message: 'Either email or phone is required',\n    path: ['email'],\n  });\n\nexport type CreateCustomerInput = z.infer<typeof createCustomerSchema>;\n\n/**\n * Update customer schema\n */\nexport const updateCustomerSchema = z.object({\n  email: z.string().email('Invalid email format').optional().nullable(),\n  phone: z\n    .string()\n    .regex(/^\\+?[0-9]{10,15}$/, 'Invalid phone number format')\n    .optional()\n    .nullable(),\n  firstName: z.string().trim().max(100).optional().nullable(),\n  lastName: z.string().trim().max(100).optional().nullable(),\n  avatar: z.string().url('Invalid URL format').optional().nullable(),\n  notes: notesSchema,\n  metadata: z.record(z.unknown()).optional(),\n});\n\nexport type UpdateCustomerInput = z.infer<typeof updateCustomerSchema>;\n\n/**\n * List customers query schema\n */\nexport const listCustomersQuerySchema = z.object({\n  search: z.string().trim().max(100).optional(),\n  minOrders: z.coerce.number().int().min(0).optional(),\n  minSpent: z.coerce.number().min(0).optional(),\n  page: z.coerce.number().int().positive().optional().default(1),\n  perPage: z.coerce.number().int().positive().max(100).optional().default(20),\n  sortBy: z.enum(['totalOrders', 'totalSpent', 'lastOrderAt', 'createdAt']).optional().default('createdAt'),\n  sortOrder: z.enum(['asc', 'desc']).optional().default('desc'),\n});\n\nexport type ListCustomersQueryInput = z.infer<typeof listCustomersQuerySchema>;\n\n// -----------------------------------------------------------------------------\n// Service Request Schemas\n// -----------------------------------------------------------------------------\n\n/**\n * Create service request schema\n */\nexport const createServiceRequestSchema = z.object({\n  tableId: cuidSchema,\n  type: serviceRequestTypeSchema,\n  message: messageSchema,\n});\n\nexport type CreateServiceRequestInput = z.infer<typeof createServiceRequestSchema>;\n\n/**\n * Resolve service request schema\n */\nexport const resolveServiceRequestSchema = z.object({\n  resolvedById: cuidSchema.optional(),\n});\n\nexport type ResolveServiceRequestInput = z.infer<typeof resolveServiceRequestSchema>;\n\n/**\n * List service requests query schema\n */\nexport const listServiceRequestsQuerySchema = z.object({\n  tableId: optionalCuidSchema,\n  isResolved: z\n    .string()\n    .transform((val) => val === 'true')\n    .optional(),\n  type: serviceRequestTypeSchema.optional(),\n  page: z.coerce.number().int().positive().optional().default(1),\n  perPage: z.coerce.number().int().positive().max(100).optional().default(50),\n});\n\nexport type ListServiceRequestsQueryInput = z.infer<typeof listServiceRequestsQuerySchema>;\n\n// -----------------------------------------------------------------------------\n// Feedback Schemas\n// -----------------------------------------------------------------------------\n\n/**\n * Create feedback schema\n */\nexport const createFeedbackSchema = z.object({\n  orderId: cuidSchema,\n  rating: ratingSchema,\n  comment: commentSchema,\n  isPublic: z.boolean().optional().default(false),\n});\n\nexport type CreateFeedbackInput = z.infer<typeof createFeedbackSchema>;\n\n/**\n * List feedback query schema\n */\nexport const listFeedbackQuerySchema = z.object({\n  minRating: z.coerce.number().int().min(1).max(5).optional(),\n  maxRating: z.coerce.number().int().min(1).max(5).optional(),\n  isPublic: z\n    .string()\n    .transform((val) => val === 'true')\n    .optional(),\n  page: z.coerce.number().int().positive().optional().default(1),\n  perPage: z.coerce.number().int().positive().max(100).optional().default(20),\n  sortBy: z.enum(['rating', 'createdAt']).optional().default('createdAt'),\n  sortOrder: z.enum(['asc', 'desc']).optional().default('desc'),\n});\n\nexport type ListFeedbackQueryInput = z.infer<typeof listFeedbackQuerySchema>;\n\n// -----------------------------------------------------------------------------\n// Module Settings Schema\n// -----------------------------------------------------------------------------\n\n/**\n * Order module settings schema\n */\nexport const orderModuleSettingsSchema = z.object({\n  defaultCurrency: z.string().length(3).toUpperCase().optional().default('TRY'),\n  orderNumberPrefix: z.string().max(10).optional().default('ORD'),\n  autoCompleteDelayMinutes: z.number().int().min(1).max(1440).optional().default(30),\n  enableTableOrdering: z.boolean().optional().default(true),\n  enableTakeaway: z.boolean().optional().default(true),\n  enableDelivery: z.boolean().optional().default(false),\n  enableServiceRequests: z.boolean().optional().default(true),\n  requireCustomerInfo: z.boolean().optional().default(false),\n  enableFeedback: z.boolean().optional().default(true),\n  feedbackReminderDelayMinutes: z.number().int().min(1).max(1440).optional().default(60),\n  taxRate: z.number().min(LIMITS.taxRate.min).max(LIMITS.taxRate.max).optional().default(10),\n  maxItemsPerOrder: z.number().int().min(LIMITS.maxItemsPerOrder.min).max(LIMITS.maxItemsPerOrder.max).optional().default(50),\n  maxOrderNoteLength: z.number().int().min(1).max(2000).optional().default(500),\n});\n\nexport type OrderModuleSettingsInput = z.infer<typeof orderModuleSettingsSchema>;\n\n// -----------------------------------------------------------------------------\n// Utility Functions\n// -----------------------------------------------------------------------------\n\n/**\n * Validates if an order status transition is allowed\n *\n * @param currentStatus - Current order status\n * @param targetStatus - Target order status\n * @returns True if transition is valid\n *\n * @example\n * ```typescript\n * const isValid = isValidStatusTransition('PENDING', 'CONFIRMED');\n * // Returns: true\n * ```\n */\nexport function isValidStatusTransition(currentStatus: string, targetStatus: string): boolean {\n  const transitions: Record<string, string[]> = {\n    PENDING: ['CONFIRMED', 'CANCELLED'],\n    CONFIRMED: ['PREPARING', 'CANCELLED'],\n    PREPARING: ['READY', 'CANCELLED'],\n    READY: ['DELIVERED'],\n    DELIVERED: ['COMPLETED'],\n    COMPLETED: [],\n    CANCELLED: [],\n  };\n\n  return transitions[currentStatus]?.includes(targetStatus) ?? false;\n}\n\n/**\n * Generates a unique order number\n *\n * @param prefix - Order number prefix (default: 'ORD')\n * @returns Unique order number\n *\n * @example\n * ```typescript\n * const orderNumber = generateOrderNumber('ORD');\n * // Returns: 'ORD-20260131-ABC123'\n * ```\n */\nexport function generateOrderNumber(prefix: string = 'ORD'): string {\n  const date = new Date();\n  const dateStr = date.toISOString().slice(0, 10).replace(/-/g, '');\n  const random = Math.random().toString(36).substring(2, 8).toUpperCase();\n  return `${prefix}-${dateStr}-${random}`;\n}\n\n/**\n * Calculates order totals\n *\n * @param items - Order items with prices\n * @param taxRate - Tax rate percentage\n * @param discountAmount - Discount amount\n * @returns Calculated totals\n *\n * @example\n * ```typescript\n * const totals = calculateOrderTotals(items, 10, 0);\n * // Returns: { subtotal: 100, taxAmount: 10, totalAmount: 110 }\n * ```\n */\nexport function calculateOrderTotals(\n  items: Array<{ quantity: number; unitPrice: number; modifiers?: Array<{ price: number; quantity: number }> }>,\n  taxRate: number,\n  discountAmount: number = 0\n): { subtotal: number; taxAmount: number; totalAmount: number } {\n  const subtotal = items.reduce((sum, item) => {\n    const itemTotal = item.quantity * item.unitPrice;\n    const modifiersTotal = (item.modifiers || []).reduce(\n      (modSum, mod) => modSum + mod.price * mod.quantity,\n      0\n    );\n    return sum + itemTotal + modifiersTotal;\n  }, 0);\n\n  const taxAmount = (subtotal - discountAmount) * (taxRate / 100);\n  const totalAmount = subtotal - discountAmount + taxAmount;\n\n  return {\n    subtotal: Math.round(subtotal * 100) / 100,\n    taxAmount: Math.round(taxAmount * 100) / 100,\n    totalAmount: Math.round(totalAmount * 100) / 100,\n  };\n}\n\n/**\n * Validates phone number format\n *\n * @param phone - Phone number to validate\n * @returns True if valid\n *\n * @example\n * ```typescript\n * const isValid = isValidPhoneNumber('+905551234567');\n * // Returns: true\n * ```\n */\nexport function isValidPhoneNumber(phone: string): boolean {\n  return /^\\+?[0-9]{10,15}$/.test(phone);\n}\n\n/**\n * Validates hex color format\n *\n * @param color - Color string to validate\n * @returns True if valid hex color\n *\n * @example\n * ```typescript\n * const isValid = isValidHexColor('#FF5733');\n * // Returns: true\n * ```\n */\nexport function isValidHexColor(color: string): boolean {\n  return HEX_COLOR_REGEX.test(color);\n}\n",
        "last_modified": "2026-02-01T09:10:53.759661"
      },
      "task_intent": {
        "title": "001-create",
        "description": "",
        "from_plan": false
      },
      "commits_behind_main": 1,
      "status": "active",
      "merged_at": null
    }
  },
  "created_at": "2026-02-01T08:03:26.466834",
  "last_updated": "2026-02-01T08:03:26.476648"
}