{
  "file_path": "src/modules/_core/module-loader/module-loader.service.ts",
  "main_branch_history": [],
  "task_views": {
    "001-create": {
      "task_id": "001-create",
      "branch_point": {
        "commit_hash": "e2c14236dedadbadc7b19d123890e3f98e7316c0",
        "content": "",
        "timestamp": "2026-02-01T08:03:23.990755"
      },
      "worktree_state": {
        "content": "/**\n * Module Loader Admin Service\n *\n * Business logic service for the Module Loader admin module.\n * Provides admin-level module management operations wrapping the kernel ModuleLoader.\n *\n * @module modules/_core/module-loader/module-loader.service\n *\n * @example\n * ```typescript\n * import { ModuleLoaderService } from '@/modules/_core/module-loader/module-loader.service';\n * import { resolve } from '@/core/kernel/container';\n *\n * const moduleService = resolve<ModuleLoaderService>('ModuleLoaderService');\n *\n * // List all modules\n * const modules = await moduleService.listModules();\n *\n * // Activate a module\n * const result = await moduleService.activateModule({ moduleId: 'menu' });\n * ```\n */\n\nimport { injectable, inject } from 'tsyringe';\n\nimport { TOKENS } from '@/core/kernel/container';\nimport { ModuleLoader, LoadedModule, ModuleStatus, ModuleCategory } from '@/core/kernel/module-loader';\nimport { AppException } from '@/core/exceptions/app.exception';\nimport { EventService } from '@/core/services/event.service';\n\nimport type {\n  ModuleInfo,\n  ModuleSummary,\n  ModuleStats,\n  ModuleListParams,\n  ModuleListResponse,\n  ModuleActionResponse,\n  ModuleActivateRequest,\n  ModuleDeactivateRequest,\n  DependencyCheckResult,\n  ModuleHealthCheckResult,\n} from '@/modules/_core/module-loader/module-loader.types';\n\nimport { toModuleInfo, toModuleSummary } from '@/modules/_core/module-loader/module-loader.types';\n\n// -----------------------------------------------------------------------------\n// Module Loader Service\n// -----------------------------------------------------------------------------\n\n/**\n * Module Loader Admin Service\n *\n * Handles all module management operations for the admin panel:\n * - List and filter modules\n * - Activate/deactivate modules\n * - Check dependencies\n * - Module health checks\n *\n * @example\n * ```typescript\n * @injectable()\n * class AdminController {\n *   constructor(\n *     @inject('ModuleLoaderService') private moduleService: ModuleLoaderService,\n *   ) {}\n *\n *   async getModules() {\n *     return this.moduleService.listModules();\n *   }\n * }\n * ```\n */\n@injectable()\nexport class ModuleLoaderService {\n  constructor(\n    @inject(TOKENS.ModuleLoader) private readonly moduleLoader: ModuleLoader,\n    @inject(TOKENS.EventService) private readonly eventService: EventService\n  ) {}\n\n  // ---------------------------------------------------------------------------\n  // Read Operations\n  // ---------------------------------------------------------------------------\n\n  /**\n   * Lists all modules with optional filtering.\n   *\n   * @param params - Query parameters\n   * @returns Module list response with stats\n   */\n  async listModules(params: ModuleListParams = {}): Promise<ModuleListResponse> {\n    let modules = this.moduleLoader.getAllModules();\n\n    // Apply filters\n    if (params.category) {\n      modules = modules.filter((m) => m.manifest.category === params.category);\n    }\n\n    if (params.status) {\n      modules = modules.filter((m) => m.status === params.status);\n    }\n\n    if (params.isCore !== undefined) {\n      modules = modules.filter((m) => m.manifest.core === params.isCore);\n    }\n\n    if (params.isEnabled !== undefined) {\n      const targetStatus = params.isEnabled ? 'active' : 'disabled';\n      modules = modules.filter((m) => (params.isEnabled ? m.status === 'active' : m.status !== 'active'));\n    }\n\n    if (params.search) {\n      const searchLower = params.search.toLowerCase();\n      modules = modules.filter(\n        (m) =>\n          m.manifest.name.toLowerCase().includes(searchLower) ||\n          m.manifest.displayName.toLowerCase().includes(searchLower) ||\n          m.manifest.description.toLowerCase().includes(searchLower)\n      );\n    }\n\n    // Apply sorting\n    const sortField = params.sortBy || 'priority';\n    const sortOrder = params.sortOrder || 'asc';\n\n    modules.sort((a, b) => {\n      let aValue: string | number;\n      let bValue: string | number;\n\n      switch (sortField) {\n        case 'name':\n          aValue = a.manifest.displayName.toLowerCase();\n          bValue = b.manifest.displayName.toLowerCase();\n          break;\n        case 'category':\n          aValue = a.manifest.category;\n          bValue = b.manifest.category;\n          break;\n        case 'status':\n          aValue = a.status;\n          bValue = b.status;\n          break;\n        case 'priority':\n        default:\n          aValue = a.manifest.priority;\n          bValue = b.manifest.priority;\n          break;\n      }\n\n      if (aValue < bValue) return sortOrder === 'asc' ? -1 : 1;\n      if (aValue > bValue) return sortOrder === 'asc' ? 1 : -1;\n      return 0;\n    });\n\n    // Convert to ModuleInfo\n    const moduleInfos = modules.map((m) => {\n      const dependents = this.moduleLoader.getModuleDependents(m.manifest.id);\n      return toModuleInfo(m, dependents);\n    });\n\n    // Build response\n    return {\n      modules: moduleInfos,\n      stats: params.includeStats !== false ? this.getStats() : this.getStats(),\n    };\n  }\n\n  /**\n   * Lists module summaries for quick display.\n   *\n   * @returns Array of module summaries\n   */\n  async listModuleSummaries(): Promise<ModuleSummary[]> {\n    const modules = this.moduleLoader.getAllModules();\n    return modules.map((m) => {\n      const info = toModuleInfo(m);\n      return toModuleSummary(info);\n    });\n  }\n\n  /**\n   * Gets module by ID.\n   *\n   * @param moduleId - Module ID\n   * @returns Module info or null\n   */\n  async getModuleById(moduleId: string): Promise<ModuleInfo | null> {\n    const module = this.moduleLoader.getModule(moduleId);\n    if (!module) {\n      return null;\n    }\n\n    const dependents = this.moduleLoader.getModuleDependents(moduleId);\n    return toModuleInfo(module, dependents);\n  }\n\n  /**\n   * Gets module by ID or throws.\n   *\n   * @param moduleId - Module ID\n   * @returns Module info\n   * @throws {AppException} If module not found\n   */\n  async getModuleByIdOrThrow(moduleId: string): Promise<ModuleInfo> {\n    const module = await this.getModuleById(moduleId);\n    if (!module) {\n      throw AppException.moduleNotFound(moduleId);\n    }\n    return module;\n  }\n\n  /**\n   * Gets active modules.\n   *\n   * @returns Array of active module infos\n   */\n  async getActiveModules(): Promise<ModuleInfo[]> {\n    const modules = this.moduleLoader.getActiveModules();\n    return modules.map((m) => {\n      const dependents = this.moduleLoader.getModuleDependents(m.manifest.id);\n      return toModuleInfo(m, dependents);\n    });\n  }\n\n  /**\n   * Gets core modules.\n   *\n   * @returns Array of core module infos\n   */\n  async getCoreModules(): Promise<ModuleInfo[]> {\n    const modules = this.moduleLoader.getCoreModules();\n    return modules.map((m) => {\n      const dependents = this.moduleLoader.getModuleDependents(m.manifest.id);\n      return toModuleInfo(m, dependents);\n    });\n  }\n\n  /**\n   * Gets modules by category.\n   *\n   * @param category - Module category\n   * @returns Array of module infos\n   */\n  async getModulesByCategory(category: ModuleCategory): Promise<ModuleInfo[]> {\n    const modules = this.moduleLoader.getModulesByCategory(category);\n    return modules.map((m) => {\n      const dependents = this.moduleLoader.getModuleDependents(m.manifest.id);\n      return toModuleInfo(m, dependents);\n    });\n  }\n\n  /**\n   * Gets modules by status.\n   *\n   * @param status - Module status\n   * @returns Array of module infos\n   */\n  async getModulesByStatus(status: ModuleStatus): Promise<ModuleInfo[]> {\n    const modules = this.moduleLoader.getModulesByStatus(status);\n    return modules.map((m) => {\n      const dependents = this.moduleLoader.getModuleDependents(m.manifest.id);\n      return toModuleInfo(m, dependents);\n    });\n  }\n\n  /**\n   * Gets module statistics.\n   *\n   * @returns Module statistics\n   */\n  getStats(): ModuleStats {\n    const kernelStats = this.moduleLoader.getStats();\n    const allModules = this.moduleLoader.getAllModules();\n\n    return {\n      total: kernelStats.total,\n      byStatus: kernelStats.byStatus,\n      byCategory: kernelStats.byCategory,\n      active: kernelStats.byStatus.active || 0,\n      core: allModules.filter((m) => m.manifest.core).length,\n      errors: kernelStats.byStatus.error || 0,\n    };\n  }\n\n  // ---------------------------------------------------------------------------\n  // Activation Operations\n  // ---------------------------------------------------------------------------\n\n  /**\n   * Activates a module.\n   *\n   * @param request - Activation request\n   * @returns Action response\n   *\n   * @example\n   * ```typescript\n   * const result = await moduleService.activateModule({ moduleId: 'menu' });\n   * if (result.success) {\n   *   console.log('Module activated:', result.module?.id);\n   * }\n   * ```\n   */\n  async activateModule(request: ModuleActivateRequest): Promise<ModuleActionResponse> {\n    const { moduleId, force } = request;\n\n    // Check module exists\n    const module = this.moduleLoader.getModule(moduleId);\n    if (!module) {\n      throw AppException.moduleNotFound(moduleId);\n    }\n\n    // Check if already active\n    if (module.status === 'active') {\n      return {\n        success: true,\n        module: await this.getModuleByIdOrThrow(moduleId),\n        message: `Module ${moduleId} is already active.`,\n      };\n    }\n\n    // Check dependencies unless forced\n    if (!force) {\n      const depCheck = this.checkDependencies(moduleId);\n      if (!depCheck.valid) {\n        if (depCheck.missing.length > 0) {\n          throw AppException.moduleDependencyError(moduleId, depCheck.missing);\n        }\n        if (depCheck.circular.length > 0) {\n          throw AppException.badRequest(\n            `Circular dependency detected for module ${moduleId}: ${depCheck.circular.join(', ')}`\n          );\n        }\n      }\n    }\n\n    // Perform activation\n    const startTime = Date.now();\n    const success = await this.moduleLoader.activateModule(moduleId);\n    const duration = Date.now() - startTime;\n\n    if (!success) {\n      const updatedModule = this.moduleLoader.getModule(moduleId);\n      throw AppException.internal(\n        `Failed to activate module ${moduleId}: ${updatedModule?.error || 'Unknown error'}`\n      );\n    }\n\n    // Emit event\n    await this.eventService.emitCustom('module.activated', {\n      moduleId,\n      version: module.manifest.version,\n      activatedAt: new Date().toISOString(),\n      duration,\n      timestamp: new Date().toISOString(),\n    });\n\n    const updatedModule = await this.getModuleByIdOrThrow(moduleId);\n\n    return {\n      success: true,\n      module: updatedModule,\n      message: `Module ${moduleId} activated successfully.`,\n    };\n  }\n\n  /**\n   * Deactivates a module.\n   *\n   * @param request - Deactivation request\n   * @returns Action response\n   */\n  async deactivateModule(request: ModuleDeactivateRequest): Promise<ModuleActionResponse> {\n    const { moduleId, force } = request;\n\n    // Check module exists\n    const module = this.moduleLoader.getModule(moduleId);\n    if (!module) {\n      throw AppException.moduleNotFound(moduleId);\n    }\n\n    // Core modules cannot be deactivated\n    if (module.manifest.core) {\n      throw AppException.coreModuleProtected(moduleId);\n    }\n\n    // Check if already inactive\n    if (module.status !== 'active') {\n      return {\n        success: true,\n        module: await this.getModuleByIdOrThrow(moduleId),\n        message: `Module ${moduleId} is already inactive.`,\n      };\n    }\n\n    // Check dependents unless forced\n    const warnings: string[] = [];\n    if (!force) {\n      const dependents = this.moduleLoader.getModuleDependents(moduleId);\n      const activeDependents = dependents.filter(\n        (depId) => this.moduleLoader.getModule(depId)?.status === 'active'\n      );\n\n      if (activeDependents.length > 0) {\n        throw AppException.badRequest(\n          `Cannot deactivate ${moduleId}: other active modules depend on it: ${activeDependents.join(', ')}`\n        );\n      }\n    } else {\n      const dependents = this.moduleLoader.getModuleDependents(moduleId);\n      const activeDependents = dependents.filter(\n        (depId) => this.moduleLoader.getModule(depId)?.status === 'active'\n      );\n      if (activeDependents.length > 0) {\n        warnings.push(`Force deactivating with active dependents: ${activeDependents.join(', ')}`);\n      }\n    }\n\n    // Perform deactivation\n    const startTime = Date.now();\n    const success = await this.moduleLoader.deactivateModule(moduleId);\n    const duration = Date.now() - startTime;\n\n    if (!success) {\n      const updatedModule = this.moduleLoader.getModule(moduleId);\n      throw AppException.internal(\n        `Failed to deactivate module ${moduleId}: ${updatedModule?.error || 'Unknown error'}`\n      );\n    }\n\n    // Emit event\n    await this.eventService.emitCustom('module.deactivated', {\n      moduleId,\n      version: module.manifest.version,\n      deactivatedAt: new Date().toISOString(),\n      duration,\n      timestamp: new Date().toISOString(),\n    });\n\n    const updatedModule = await this.getModuleByIdOrThrow(moduleId);\n\n    return {\n      success: true,\n      module: updatedModule,\n      message: `Module ${moduleId} deactivated successfully.`,\n      warnings: warnings.length > 0 ? warnings : undefined,\n    };\n  }\n\n  // ---------------------------------------------------------------------------\n  // Dependency Operations\n  // ---------------------------------------------------------------------------\n\n  /**\n   * Checks module dependencies.\n   *\n   * @param moduleId - Module ID to check (optional, checks all if not provided)\n   * @returns Dependency check result\n   */\n  checkDependencies(moduleId?: string): DependencyCheckResult {\n    const resolution = this.moduleLoader.resolveDependencies(moduleId ? [moduleId] : undefined);\n\n    // Check for available optional dependencies\n    const availableOptional: string[] = [];\n    if (moduleId) {\n      const module = this.moduleLoader.getModule(moduleId);\n      if (module) {\n        for (const optDep of module.manifest.dependencies.optional) {\n          const depModule = this.moduleLoader.getModule(optDep);\n          if (depModule && depModule.status === 'active') {\n            availableOptional.push(optDep);\n          }\n        }\n      }\n    }\n\n    return {\n      valid: resolution.resolved,\n      missing: resolution.missing,\n      circular: resolution.circular,\n      availableOptional,\n      loadOrder: resolution.loadOrder,\n    };\n  }\n\n  /**\n   * Gets module dependents (modules that depend on this one).\n   *\n   * @param moduleId - Module ID\n   * @returns Array of dependent module IDs\n   */\n  getModuleDependents(moduleId: string): string[] {\n    return this.moduleLoader.getModuleDependents(moduleId);\n  }\n\n  /**\n   * Checks if a module is available and active.\n   *\n   * @param moduleId - Module ID\n   * @returns True if module is active\n   */\n  isModuleActive(moduleId: string): boolean {\n    return this.moduleLoader.isModuleActive(moduleId);\n  }\n\n  // ---------------------------------------------------------------------------\n  // Health Check Operations\n  // ---------------------------------------------------------------------------\n\n  /**\n   * Performs health check on a module.\n   *\n   * @param moduleId - Module ID\n   * @returns Health check result\n   */\n  async checkModuleHealth(moduleId: string): Promise<ModuleHealthCheckResult> {\n    const module = this.moduleLoader.getModule(moduleId);\n\n    if (!module) {\n      return {\n        moduleId,\n        status: 'unhealthy',\n        message: 'Module not found',\n        checkedAt: new Date(),\n      };\n    }\n\n    // Check based on status\n    if (module.status === 'error') {\n      return {\n        moduleId,\n        status: 'unhealthy',\n        message: module.error || 'Module in error state',\n        details: { error: module.error },\n        checkedAt: new Date(),\n      };\n    }\n\n    if (module.status !== 'active') {\n      return {\n        moduleId,\n        status: 'degraded',\n        message: `Module not active (status: ${module.status})`,\n        details: { status: module.status },\n        checkedAt: new Date(),\n      };\n    }\n\n    // Check dependencies\n    const depCheck = this.checkDependencies(moduleId);\n    if (!depCheck.valid) {\n      return {\n        moduleId,\n        status: 'degraded',\n        message: 'Some dependencies are not satisfied',\n        details: {\n          missing: depCheck.missing,\n          circular: depCheck.circular,\n        },\n        checkedAt: new Date(),\n      };\n    }\n\n    return {\n      moduleId,\n      status: 'healthy',\n      message: 'Module is healthy',\n      details: {\n        version: module.manifest.version,\n        loadedAt: module.loadedAt?.toISOString(),\n      },\n      checkedAt: new Date(),\n    };\n  }\n\n  /**\n   * Performs health check on all active modules.\n   *\n   * @returns Array of health check results\n   */\n  async checkAllModulesHealth(): Promise<ModuleHealthCheckResult[]> {\n    const activeModules = this.moduleLoader.getActiveModules();\n    const results: ModuleHealthCheckResult[] = [];\n\n    for (const module of activeModules) {\n      const result = await this.checkModuleHealth(module.manifest.id);\n      results.push(result);\n    }\n\n    return results;\n  }\n\n  // ---------------------------------------------------------------------------\n  // Discovery Operations\n  // ---------------------------------------------------------------------------\n\n  /**\n   * Triggers module discovery (scans for new modules).\n   *\n   * @returns Array of newly discovered module IDs\n   */\n  async discoverModules(): Promise<string[]> {\n    return this.moduleLoader.discoverModules();\n  }\n\n  /**\n   * Gets all permissions from active modules.\n   *\n   * @returns Array of permission strings\n   */\n  getAllPermissions(): string[] {\n    return this.moduleLoader.getAllPermissions();\n  }\n\n  /**\n   * Gets admin menu items from active modules.\n   *\n   * @returns Array of admin menu configurations\n   */\n  getAdminMenuItems(): Array<{ moduleId: string; menu: { label: string; icon?: string; position: number } }> {\n    return this.moduleLoader.getAdminMenuItems();\n  }\n}\n",
        "last_modified": "2026-02-01T09:10:53.708704"
      },
      "task_intent": {
        "title": "001-create",
        "description": "",
        "from_plan": false
      },
      "commits_behind_main": 1,
      "status": "active",
      "merged_at": null
    }
  },
  "created_at": "2026-02-01T08:03:25.158109",
  "last_updated": "2026-02-01T08:03:25.168153"
}