{
  "file_path": "src/modules/order/order.events.ts",
  "main_branch_history": [],
  "task_views": {
    "001-create": {
      "task_id": "001-create",
      "branch_point": {
        "commit_hash": "e2c14236dedadbadc7b19d123890e3f98e7316c0",
        "content": "",
        "timestamp": "2026-02-01T08:03:23.990755"
      },
      "worktree_state": {
        "content": "/**\n * Order Module Events\n *\n * Event definitions and emitters for the Order module.\n * Provides typed domain events for order, table, zone, QR code,\n * customer, service request, and feedback operations.\n *\n * @module modules/order/order.events\n *\n * @example\n * ```typescript\n * import { OrderModuleEvents, emitOrderCreated } from '@/modules/order/order.events';\n *\n * // Emit an order created event\n * await emitOrderCreated(eventService, {\n *   orderId: 'ord_123',\n *   orderNumber: 'ORD-20260201-001',\n *   organizationId: 'org_456',\n *   type: 'DINE_IN',\n *   totalAmount: 250.00,\n *   tableId: 'table_789',\n * });\n * ```\n */\n\nimport type { EventService } from '@/core/services/event.service';\nimport type {\n  OrderStatus,\n  OrderType,\n  TableStatus,\n  OrderItemStatus,\n  ServiceRequestType,\n} from '@/modules/order/order.types';\n\n// -----------------------------------------------------------------------------\n// Base Event Types\n// -----------------------------------------------------------------------------\n\n/**\n * Base event payload with common fields\n */\nexport interface BaseEventPayload {\n  /** Organization ID */\n  organizationId: string;\n  /** Event timestamp */\n  timestamp: string;\n  /** User who triggered the event */\n  triggeredBy?: string;\n}\n\n// -----------------------------------------------------------------------------\n// Order Event Types\n// -----------------------------------------------------------------------------\n\n/**\n * Order created event payload\n */\nexport interface OrderCreatedEventPayload extends BaseEventPayload {\n  /** Order ID */\n  orderId: string;\n  /** Order number */\n  orderNumber: string;\n  /** Order type */\n  type: OrderType;\n  /** Total amount */\n  totalAmount: number;\n  /** Table ID (if dine-in) */\n  tableId: string | null;\n  /** Customer ID (if registered) */\n  customerId: string | null;\n  /** Item count */\n  itemCount: number;\n}\n\n/**\n * Order updated event payload\n */\nexport interface OrderUpdatedEventPayload extends BaseEventPayload {\n  /** Order ID */\n  orderId: string;\n  /** Order number */\n  orderNumber: string;\n  /** Changed fields */\n  changes: Record<string, unknown>;\n  /** Updated by user ID */\n  updatedBy?: string;\n}\n\n/**\n * Order status changed event payload\n */\nexport interface OrderStatusChangedEventPayload extends BaseEventPayload {\n  /** Order ID */\n  orderId: string;\n  /** Order number */\n  orderNumber: string;\n  /** Previous status */\n  previousStatus: OrderStatus;\n  /** New status */\n  newStatus: OrderStatus;\n  /** Cancel reason (if cancelled) */\n  cancelReason: string | null;\n  /** Changed by user ID */\n  changedBy?: string;\n}\n\n/**\n * Order confirmed event payload\n */\nexport interface OrderConfirmedEventPayload extends BaseEventPayload {\n  /** Order ID */\n  orderId: string;\n  /** Order number */\n  orderNumber: string;\n  /** Confirmed at timestamp */\n  confirmedAt: string;\n  /** Confirmed by user ID */\n  confirmedBy?: string;\n}\n\n/**\n * Order preparing event payload\n */\nexport interface OrderPreparingEventPayload extends BaseEventPayload {\n  /** Order ID */\n  orderId: string;\n  /** Order number */\n  orderNumber: string;\n  /** Started at timestamp */\n  startedAt: string;\n}\n\n/**\n * Order ready event payload\n */\nexport interface OrderReadyEventPayload extends BaseEventPayload {\n  /** Order ID */\n  orderId: string;\n  /** Order number */\n  orderNumber: string;\n  /** Ready at timestamp */\n  readyAt: string;\n  /** Preparation time in minutes */\n  prepTimeMinutes: number;\n}\n\n/**\n * Order delivered event payload\n */\nexport interface OrderDeliveredEventPayload extends BaseEventPayload {\n  /** Order ID */\n  orderId: string;\n  /** Order number */\n  orderNumber: string;\n  /** Delivered at timestamp */\n  deliveredAt: string;\n  /** Delivered by user ID */\n  deliveredBy?: string;\n}\n\n/**\n * Order completed event payload\n */\nexport interface OrderCompletedEventPayload extends BaseEventPayload {\n  /** Order ID */\n  orderId: string;\n  /** Order number */\n  orderNumber: string;\n  /** Completed at timestamp */\n  completedAt: string;\n  /** Total amount */\n  totalAmount: number;\n  /** Order duration in minutes */\n  durationMinutes: number;\n}\n\n/**\n * Order cancelled event payload\n */\nexport interface OrderCancelledEventPayload extends BaseEventPayload {\n  /** Order ID */\n  orderId: string;\n  /** Order number */\n  orderNumber: string;\n  /** Cancelled at timestamp */\n  cancelledAt: string;\n  /** Cancellation reason */\n  reason: string;\n  /** Previous status before cancellation */\n  previousStatus: OrderStatus;\n  /** Cancelled by user ID */\n  cancelledBy?: string;\n}\n\n// -----------------------------------------------------------------------------\n// Order Item Event Types\n// -----------------------------------------------------------------------------\n\n/**\n * Order item added event payload\n */\nexport interface OrderItemAddedEventPayload extends BaseEventPayload {\n  /** Order ID */\n  orderId: string;\n  /** Order number */\n  orderNumber: string;\n  /** Item ID */\n  itemId: string;\n  /** Product ID */\n  productId: string;\n  /** Product name */\n  productName: string;\n  /** Quantity */\n  quantity: number;\n  /** Added by user ID */\n  addedBy?: string;\n}\n\n/**\n * Order item updated event payload\n */\nexport interface OrderItemUpdatedEventPayload extends BaseEventPayload {\n  /** Order ID */\n  orderId: string;\n  /** Order number */\n  orderNumber: string;\n  /** Item ID */\n  itemId: string;\n  /** Changed fields */\n  changes: Record<string, unknown>;\n  /** Updated by user ID */\n  updatedBy?: string;\n}\n\n/**\n * Order item removed event payload\n */\nexport interface OrderItemRemovedEventPayload extends BaseEventPayload {\n  /** Order ID */\n  orderId: string;\n  /** Order number */\n  orderNumber: string;\n  /** Item ID */\n  itemId: string;\n  /** Product name (for logging) */\n  productName: string;\n  /** Removed by user ID */\n  removedBy?: string;\n}\n\n/**\n * Order item status changed event payload\n */\nexport interface OrderItemStatusChangedEventPayload extends BaseEventPayload {\n  /** Order ID */\n  orderId: string;\n  /** Order number */\n  orderNumber: string;\n  /** Item ID */\n  itemId: string;\n  /** Previous status */\n  previousStatus: OrderItemStatus;\n  /** New status */\n  newStatus: OrderItemStatus;\n  /** Changed by user ID */\n  changedBy?: string;\n}\n\n// -----------------------------------------------------------------------------\n// Table Event Types\n// -----------------------------------------------------------------------------\n\n/**\n * Table created event payload\n */\nexport interface TableCreatedEventPayload extends BaseEventPayload {\n  /** Table ID */\n  tableId: string;\n  /** Table number */\n  tableNumber: string;\n  /** Zone ID */\n  zoneId: string | null;\n  /** Capacity */\n  capacity: number;\n  /** Created by user ID */\n  createdBy?: string;\n}\n\n/**\n * Table updated event payload\n */\nexport interface TableUpdatedEventPayload extends BaseEventPayload {\n  /** Table ID */\n  tableId: string;\n  /** Table number */\n  tableNumber: string;\n  /** Changed fields */\n  changes: Record<string, unknown>;\n  /** Updated by user ID */\n  updatedBy?: string;\n}\n\n/**\n * Table deleted event payload\n */\nexport interface TableDeletedEventPayload extends BaseEventPayload {\n  /** Table ID */\n  tableId: string;\n  /** Table number */\n  tableNumber: string;\n  /** Deleted by user ID */\n  deletedBy?: string;\n}\n\n/**\n * Table status changed event payload\n */\nexport interface TableStatusChangedEventPayload extends BaseEventPayload {\n  /** Table ID */\n  tableId: string;\n  /** Table number */\n  tableNumber: string;\n  /** Previous status */\n  previousStatus: TableStatus;\n  /** New status */\n  newStatus: TableStatus;\n  /** Associated order ID (if occupied) */\n  orderId: string | null;\n  /** Changed by user ID */\n  changedBy?: string;\n}\n\n// -----------------------------------------------------------------------------\n// Zone Event Types\n// -----------------------------------------------------------------------------\n\n/**\n * Zone created event payload\n */\nexport interface ZoneCreatedEventPayload extends BaseEventPayload {\n  /** Zone ID */\n  zoneId: string;\n  /** Zone name */\n  name: string;\n  /** Zone color */\n  color: string | null;\n  /** Created by user ID */\n  createdBy?: string;\n}\n\n/**\n * Zone updated event payload\n */\nexport interface ZoneUpdatedEventPayload extends BaseEventPayload {\n  /** Zone ID */\n  zoneId: string;\n  /** Zone name */\n  name: string;\n  /** Changed fields */\n  changes: Record<string, unknown>;\n  /** Updated by user ID */\n  updatedBy?: string;\n}\n\n/**\n * Zone deleted event payload\n */\nexport interface ZoneDeletedEventPayload extends BaseEventPayload {\n  /** Zone ID */\n  zoneId: string;\n  /** Zone name */\n  name: string;\n  /** Deleted by user ID */\n  deletedBy?: string;\n}\n\n// -----------------------------------------------------------------------------\n// QR Code Event Types\n// -----------------------------------------------------------------------------\n\n/**\n * QR code created event payload\n */\nexport interface QRCodeCreatedEventPayload extends BaseEventPayload {\n  /** QR Code ID */\n  qrCodeId: string;\n  /** Unique code */\n  code: string;\n  /** Menu ID */\n  menuId: string;\n  /** Table ID (if table QR) */\n  tableId: string | null;\n  /** QR code type */\n  type: string;\n  /** Created by user ID */\n  createdBy?: string;\n}\n\n/**\n * QR code scanned event payload\n */\nexport interface QRCodeScannedEventPayload extends BaseEventPayload {\n  /** QR Code ID */\n  qrCodeId: string;\n  /** Unique code */\n  code: string;\n  /** Menu ID */\n  menuId: string;\n  /** Table ID (if table QR) */\n  tableId: string | null;\n  /** Scan metadata */\n  scanData: {\n    /** User agent */\n    userAgent: string | null;\n    /** Device type */\n    deviceType: string | null;\n    /** Browser */\n    browser: string | null;\n    /** Operating system */\n    os: string | null;\n    /** Country */\n    country: string | null;\n    /** City */\n    city: string | null;\n  };\n}\n\n/**\n * QR code deleted event payload\n */\nexport interface QRCodeDeletedEventPayload extends BaseEventPayload {\n  /** QR Code ID */\n  qrCodeId: string;\n  /** Unique code */\n  code: string;\n  /** Deleted by user ID */\n  deletedBy?: string;\n}\n\n// -----------------------------------------------------------------------------\n// Customer Event Types\n// -----------------------------------------------------------------------------\n\n/**\n * Customer created event payload\n */\nexport interface CustomerCreatedEventPayload extends BaseEventPayload {\n  /** Customer ID */\n  customerId: string;\n  /** Email */\n  email: string | null;\n  /** Phone */\n  phone: string | null;\n  /** Full name */\n  fullName: string | null;\n}\n\n/**\n * Customer updated event payload\n */\nexport interface CustomerUpdatedEventPayload extends BaseEventPayload {\n  /** Customer ID */\n  customerId: string;\n  /** Changed fields */\n  changes: Record<string, unknown>;\n  /** Updated by user ID */\n  updatedBy?: string;\n}\n\n// -----------------------------------------------------------------------------\n// Service Request Event Types\n// -----------------------------------------------------------------------------\n\n/**\n * Service requested event payload\n */\nexport interface ServiceRequestedEventPayload extends BaseEventPayload {\n  /** Request ID */\n  requestId: string;\n  /** Table ID */\n  tableId: string;\n  /** Table number */\n  tableNumber: string;\n  /** Request type */\n  type: ServiceRequestType;\n  /** Custom message */\n  message: string | null;\n}\n\n/**\n * Service resolved event payload\n */\nexport interface ServiceResolvedEventPayload extends BaseEventPayload {\n  /** Request ID */\n  requestId: string;\n  /** Table ID */\n  tableId: string;\n  /** Table number */\n  tableNumber: string;\n  /** Request type */\n  type: string;\n  /** Resolved at timestamp */\n  resolvedAt: string;\n  /** Wait time in minutes */\n  waitTimeMinutes: number;\n  /** Resolved by user ID */\n  resolvedBy?: string;\n}\n\n// -----------------------------------------------------------------------------\n// Feedback Event Types\n// -----------------------------------------------------------------------------\n\n/**\n * Feedback submitted event payload\n */\nexport interface FeedbackSubmittedEventPayload extends BaseEventPayload {\n  /** Feedback ID */\n  feedbackId: string;\n  /** Order ID */\n  orderId: string;\n  /** Order number */\n  orderNumber: string;\n  /** Customer ID */\n  customerId: string | null;\n  /** Rating (1-5) */\n  rating: number;\n  /** Has comment */\n  hasComment: boolean;\n  /** Is public */\n  isPublic: boolean;\n}\n\n// -----------------------------------------------------------------------------\n// Order Module Events Map\n// -----------------------------------------------------------------------------\n\n/**\n * Order module domain events map\n */\nexport interface OrderModuleEvents {\n  // Order lifecycle events\n  'order.created': OrderCreatedEventPayload;\n  'order.updated': OrderUpdatedEventPayload;\n  'order.status_changed': OrderStatusChangedEventPayload;\n  'order.confirmed': OrderConfirmedEventPayload;\n  'order.preparing': OrderPreparingEventPayload;\n  'order.ready': OrderReadyEventPayload;\n  'order.delivered': OrderDeliveredEventPayload;\n  'order.completed': OrderCompletedEventPayload;\n  'order.cancelled': OrderCancelledEventPayload;\n\n  // Order item events\n  'order.item_added': OrderItemAddedEventPayload;\n  'order.item_updated': OrderItemUpdatedEventPayload;\n  'order.item_removed': OrderItemRemovedEventPayload;\n  'order.item_status_changed': OrderItemStatusChangedEventPayload;\n\n  // Table events\n  'table.created': TableCreatedEventPayload;\n  'table.updated': TableUpdatedEventPayload;\n  'table.deleted': TableDeletedEventPayload;\n  'table.status_changed': TableStatusChangedEventPayload;\n\n  // Zone events\n  'zone.created': ZoneCreatedEventPayload;\n  'zone.updated': ZoneUpdatedEventPayload;\n  'zone.deleted': ZoneDeletedEventPayload;\n\n  // QR code events\n  'qrcode.created': QRCodeCreatedEventPayload;\n  'qrcode.scanned': QRCodeScannedEventPayload;\n  'qrcode.deleted': QRCodeDeletedEventPayload;\n\n  // Customer events\n  'customer.created': CustomerCreatedEventPayload;\n  'customer.updated': CustomerUpdatedEventPayload;\n\n  // Service request events\n  'service.requested': ServiceRequestedEventPayload;\n  'service.resolved': ServiceResolvedEventPayload;\n\n  // Feedback events\n  'feedback.submitted': FeedbackSubmittedEventPayload;\n}\n\n/**\n * Order module event names\n */\nexport type OrderModuleEventName = keyof OrderModuleEvents;\n\n/**\n * All order module event names as an array\n */\nexport const ORDER_MODULE_EVENTS: OrderModuleEventName[] = [\n  // Order lifecycle events\n  'order.created',\n  'order.updated',\n  'order.status_changed',\n  'order.confirmed',\n  'order.preparing',\n  'order.ready',\n  'order.delivered',\n  'order.completed',\n  'order.cancelled',\n\n  // Order item events\n  'order.item_added',\n  'order.item_updated',\n  'order.item_removed',\n  'order.item_status_changed',\n\n  // Table events\n  'table.created',\n  'table.updated',\n  'table.deleted',\n  'table.status_changed',\n\n  // Zone events\n  'zone.created',\n  'zone.updated',\n  'zone.deleted',\n\n  // QR code events\n  'qrcode.created',\n  'qrcode.scanned',\n  'qrcode.deleted',\n\n  // Customer events\n  'customer.created',\n  'customer.updated',\n\n  // Service request events\n  'service.requested',\n  'service.resolved',\n\n  // Feedback events\n  'feedback.submitted',\n];\n\n// -----------------------------------------------------------------------------\n// Event Emitter Helpers\n// -----------------------------------------------------------------------------\n\n/**\n * Helper function to create timestamp\n */\nfunction timestamp(): string {\n  return new Date().toISOString();\n}\n\n/**\n * Emits an order created event\n */\nexport async function emitOrderCreated(\n  eventService: EventService,\n  payload: Omit<OrderCreatedEventPayload, 'timestamp'>\n): Promise<void> {\n  await eventService.emitCustom('order.created', {\n    ...payload,\n    timestamp: timestamp(),\n  });\n}\n\n/**\n * Emits an order updated event\n */\nexport async function emitOrderUpdated(\n  eventService: EventService,\n  payload: Omit<OrderUpdatedEventPayload, 'timestamp'>\n): Promise<void> {\n  await eventService.emitCustom('order.updated', {\n    ...payload,\n    timestamp: timestamp(),\n  });\n}\n\n/**\n * Emits an order status changed event\n */\nexport async function emitOrderStatusChanged(\n  eventService: EventService,\n  payload: Omit<OrderStatusChangedEventPayload, 'timestamp'>\n): Promise<void> {\n  await eventService.emitCustom('order.status_changed', {\n    ...payload,\n    timestamp: timestamp(),\n  });\n}\n\n/**\n * Emits an order confirmed event\n */\nexport async function emitOrderConfirmed(\n  eventService: EventService,\n  payload: Omit<OrderConfirmedEventPayload, 'timestamp'>\n): Promise<void> {\n  await eventService.emitCustom('order.confirmed', {\n    ...payload,\n    timestamp: timestamp(),\n  });\n}\n\n/**\n * Emits an order completed event\n */\nexport async function emitOrderCompleted(\n  eventService: EventService,\n  payload: Omit<OrderCompletedEventPayload, 'timestamp'>\n): Promise<void> {\n  await eventService.emitCustom('order.completed', {\n    ...payload,\n    timestamp: timestamp(),\n  });\n}\n\n/**\n * Emits an order cancelled event\n */\nexport async function emitOrderCancelled(\n  eventService: EventService,\n  payload: Omit<OrderCancelledEventPayload, 'timestamp'>\n): Promise<void> {\n  await eventService.emitCustom('order.cancelled', {\n    ...payload,\n    timestamp: timestamp(),\n  });\n}\n\n/**\n * Emits an order item added event\n */\nexport async function emitOrderItemAdded(\n  eventService: EventService,\n  payload: Omit<OrderItemAddedEventPayload, 'timestamp'>\n): Promise<void> {\n  await eventService.emitCustom('order.item_added', {\n    ...payload,\n    timestamp: timestamp(),\n  });\n}\n\n/**\n * Emits a table created event\n */\nexport async function emitTableCreated(\n  eventService: EventService,\n  payload: Omit<TableCreatedEventPayload, 'timestamp'>\n): Promise<void> {\n  await eventService.emitCustom('table.created', {\n    ...payload,\n    timestamp: timestamp(),\n  });\n}\n\n/**\n * Emits a table status changed event\n */\nexport async function emitTableStatusChanged(\n  eventService: EventService,\n  payload: Omit<TableStatusChangedEventPayload, 'timestamp'>\n): Promise<void> {\n  await eventService.emitCustom('table.status_changed', {\n    ...payload,\n    timestamp: timestamp(),\n  });\n}\n\n/**\n * Emits a QR code scanned event\n */\nexport async function emitQRCodeScanned(\n  eventService: EventService,\n  payload: Omit<QRCodeScannedEventPayload, 'timestamp'>\n): Promise<void> {\n  await eventService.emitCustom('qrcode.scanned', {\n    ...payload,\n    timestamp: timestamp(),\n  });\n}\n\n/**\n * Emits a service requested event\n */\nexport async function emitServiceRequested(\n  eventService: EventService,\n  payload: Omit<ServiceRequestedEventPayload, 'timestamp'>\n): Promise<void> {\n  await eventService.emitCustom('service.requested', {\n    ...payload,\n    timestamp: timestamp(),\n  });\n}\n\n/**\n * Emits a feedback submitted event\n */\nexport async function emitFeedbackSubmitted(\n  eventService: EventService,\n  payload: Omit<FeedbackSubmittedEventPayload, 'timestamp'>\n): Promise<void> {\n  await eventService.emitCustom('feedback.submitted', {\n    ...payload,\n    timestamp: timestamp(),\n  });\n}\n\n// -----------------------------------------------------------------------------\n// Export All Event Types\n// -----------------------------------------------------------------------------\n\nexport type {\n  BaseEventPayload,\n  OrderCreatedEventPayload,\n  OrderUpdatedEventPayload,\n  OrderStatusChangedEventPayload,\n  OrderConfirmedEventPayload,\n  OrderPreparingEventPayload,\n  OrderReadyEventPayload,\n  OrderDeliveredEventPayload,\n  OrderCompletedEventPayload,\n  OrderCancelledEventPayload,\n  OrderItemAddedEventPayload,\n  OrderItemUpdatedEventPayload,\n  OrderItemRemovedEventPayload,\n  OrderItemStatusChangedEventPayload,\n  TableCreatedEventPayload,\n  TableUpdatedEventPayload,\n  TableDeletedEventPayload,\n  TableStatusChangedEventPayload,\n  ZoneCreatedEventPayload,\n  ZoneUpdatedEventPayload,\n  ZoneDeletedEventPayload,\n  QRCodeCreatedEventPayload,\n  QRCodeScannedEventPayload,\n  QRCodeDeletedEventPayload,\n  CustomerCreatedEventPayload,\n  CustomerUpdatedEventPayload,\n  ServiceRequestedEventPayload,\n  ServiceResolvedEventPayload,\n  FeedbackSubmittedEventPayload,\n};\n",
        "last_modified": "2026-02-01T09:10:53.757795"
      },
      "task_intent": {
        "title": "001-create",
        "description": "",
        "from_plan": false
      },
      "commits_behind_main": 1,
      "status": "active",
      "merged_at": null
    }
  },
  "created_at": "2026-02-01T08:03:26.424839",
  "last_updated": "2026-02-01T08:03:26.434253"
}